CHANGELOG
LICENSE
MANIFEST.in
README
VERSION
setup.py
bscearth/__init__.py
bscearth.utils.egg-info/PKG-INFO
bscearth.utils.egg-info/SOURCES.txt
bscearth.utils.egg-info/dependency_links.txt
bscearth.utils.egg-info/namespace_packages.txt
bscearth.utils.egg-info/not-zip-safe
bscearth.utils.egg-info/requires.txt
bscearth.utils.egg-info/top_level.txt
bscearth/utils/__init__.py
bscearth/utils/config_parser.py
bscearth/utils/date.py
bscearth/utils/log.py
bscearth/utils/path.py