Metadata-Version: 1.1
Name: bscearth.utils
Version: 0.5.2
Summary: Shared code and tools for various BSC-ES department projects (https://earth.bsc.es/wiki/)
Home-page: https://earth.bsc.es/gitlab/ces/bscearth.utils
Author: CES Group at BSC-ES department
Author-email: ces@bsc.es
License: MIT
Download-URL: https://earth.bsc.es/gitlab/ces/bscearth.utils/repository/archive.tar.gz?ref=v0.5.2
Platform: UNKNOWN
